data_preprocessing_lib/__init__.py
data_preprocessing_lib/categorical_encoder.py
data_preprocessing_lib/data_type_converter.py
data_preprocessing_lib/datetime_handler.py
data_preprocessing_lib/feature_engineer.py
data_preprocessing_lib/missing_value_handler.py
data_preprocessing_lib/outlier_handler.py
data_preprocessing_lib/scaler.py
data_preprocessing_lib/text_cleaner.py
tests/__init__.py
tests/test_categorical_encoder.py
tests/test_data_type_converter.py
tests/test_datetime_handler.py
tests/test_feature_engineer.py
tests/test_missing_value_handler.py
tests/test_outlier_handler.py
tests/test_scaler.py
tests/test_text_cleaner.py
dataprep_lib_bayraker_bargan-0.1.0.dist-info/METADATA
dataprep_lib_bayraker_bargan-0.1.0.dist-info/WHEEL
dataprep_lib_bayraker_bargan-0.1.0.dist-info/top_level.txt
dataprep_lib_bayraker_bargan-0.1.0.dist-info/RECORD
